{
  "symbol": "USDJPYc",
  "asset_type": "forex",
  "binance_symbol": null,
  "pip_value": 0.01,
  "min_lot_size": 0.01,
  "max_lot_size": 1.0,
  "lot_step": 0.01,
  "vwap": {
    "session_anchor": "tokyo",
    "sigma_window_minutes": 60,
    "min_volume_threshold": 0.01,
    "price_precision": 3
  },
  "atr": {
    "m1_period": 14,
    "m5_period": 14,
    "ratio_multiplier": 1.0,
    "high_volatility_threshold": 2.0
  },
  "delta": {
    "spike_threshold": 1.5,
    "min_volume": 0.01,
    "lookback_periods": 20
  },
  "micro_bos": {
    "bar_lookback": 5,
    "min_atr_displacement": 0.25,
    "cooldown_period_ms": 300000
  },
  "spread_filter": {
    "normal_spread_threshold": 0.3,
    "elevated_spread_threshold": 0.6,
    "high_spread_threshold": 1.2,
    "extreme_spread_threshold": 2.4,
    "window_size": 20,
    "outlier_z_score": 2.0
  },
  "risk": {
    "max_lot_size": 0.1,
    "daily_lot_limit": 1.0,
    "hourly_lot_limit": 0.5,
    "max_drawdown_pct": 3.0,
    "circuit_breaker_threshold": 0.015
  },
  "enabled": true,
  "priority": 2
}
