{
  "config_version": "2026-01-08",
  "rmag_smoothing": {
    "enabled": true,
    "alpha": 0.3
  },
  "execution_buffers": {
    "XAUUSDc": {
      "default": 3.0,
      "high_vol": 5.0,
      "low_vol": 2.0
    },
    "BTCUSDc": {
      "default": 30.0,
      "high_vol": 50.0,
      "low_vol": 20.0
    },
    "EURUSDc": {
      "default": 0.0003,
      "high_vol": 0.0005,
      "low_vol": 0.0002
    },
    "GBPUSDc": {
      "default": 0.0003,
      "high_vol": 0.0005,
      "low_vol": 0.0002
    }
  },
  "kill_switch": {
    "enabled": true,
    "rmag_threshold": 3.0,
    "symbol_overrides": {
      "BTCUSDc": 3.5,
      "XAUUSDc": 2.8
    }
  }
}
